secure_log/__init__.py
secure_log/secure_log.py
secure_log-0.1.1.dist-info/LICENSE
secure_log-0.1.1.dist-info/METADATA
secure_log-0.1.1.dist-info/WHEEL
secure_log-0.1.1.dist-info/top_level.txt
secure_log-0.1.1.dist-info/RECORD
