Metadata-Version: 2.1
Name: secure-log
Version: 0.1.1
Summary: A package for secure logging
Author: Samuel Olusola
Author-email: sola@onboardbase.com
Project-URL: Source, https://github.com/Onboardbase/secure-log-py
Keywords: secure logging package
Classifier: Intended Audience :: Developers
Classifier: License :: OSI Approved :: MIT License
Classifier: Programming Language :: Python
Classifier: Programming Language :: Python :: 3
Classifier: Programming Language :: Python :: 3.6
Classifier: Programming Language :: Python :: 3.7
Classifier: Programming Language :: Python :: 3.8
Classifier: Programming Language :: Python :: 3.9
License-File: LICENSE
